thanosql_magic/__init__.py
thanosql_magic/exception.py
thanosql_magic/magic.py
thanosql_magic/parse.py
thanosql_magic/util.py
thanosql_magic-0.4.0.dist-info/LICENSE
thanosql_magic-0.4.0.dist-info/METADATA
thanosql_magic-0.4.0.dist-info/WHEEL
thanosql_magic-0.4.0.dist-info/top_level.txt
thanosql_magic-0.4.0.dist-info/RECORD
