Metadata-Version: 2.1
Name: thanosql-magic
Version: 0.4.0
Summary: ThanoSQL Magic
Home-page: https://github.com/smartmind-team/thanosql-magic
Author: Dada Ahn
Author-email: dada.ahn@smartmind.team
License: MIT
Keywords: smartmind thanosql ipython jupyter
Classifier: Intended Audience :: Developers
Classifier: Programming Language :: Python :: 3
Classifier: License :: OSI Approved :: MIT License
Classifier: Operating System :: OS Independent
License-File: LICENSE
Requires-Dist: ipython
Requires-Dist: requests
Requires-Dist: pandas
Requires-Dist: websocket-client
Requires-Dist: pglast
